{
  "slug": "diemtigen",
  "name": "Diemtigen",
  "canton": "BE",
  "score_total": 44.31,
  "scores": {
    "total": 44.31,
    "base": 41.53,
    "access": 48.47,
    "sub": {
      "anti_overtourism": 97.95,
      "walkability": 0.0,
      "local_hiking": 23.56,
      "water": 2.2,
      "heritage": 70.0,
      "climate": 50.0,
      "scenic_transport": 21.58,
      "destination_pull": 79.56,
      "cultural_access": 50.0,
      "access_hiking": 37.54
    }
  },
  "reachable_tags": [
    "Hiking",
    "Water",
    "Scenic transport",
    "Museums",
    "Historic town"
  ],
  "metrics": {
    "overnight_stays": 12183,
    "domestic_share_overnights": 0.799,
    "summer_temp_avg": 16.07,
    "local_hiking_m": 40697.6,
    "regional_hiking_m": 911522.9,
    "walkability_path_m": 0.0,
    "scenic_transport_count": 20,
    "reachable_named_museums": "10",
    "isos_name": "Diemtigen",
    "isos_kategorie": "Dorf"
  },
  "data_status": {
    "bfs": true,
    "climate": true,
    "water": true,
    "heritage": true,
    "hiking": true,
    "walkability": true,
    "scenic": true,
    "dest_pull": true,
    "cultural": true
  },
  "rank": 99,
  "seasonality": {
    "volatility_label": "Strongly seasonal",
    "peak_month": "jul",
    "trough_month": "apr",
    "peak_trough_ratio": 5.67,
    "monthly_index": [
      115,
      144,
      55,
      35,
      114,
      90,
      199,
      160,
      100,
      107,
      41,
      39
    ]
  },
  "tourism_intensity": 4.4,
  "restaurant_count": 1,
  "isos_name": "Diemtigen",
  "reachable_slugs": [
    "aeschi-bei-spiez",
    "reichenbach-im-kandertal",
    "spiez",
    "thun"
  ]
}