{
  "slug": "locarno",
  "name": "Locarno",
  "canton": "TI",
  "score_total": 62.0,
  "reachable_tags": [
    "Hiking",
    "Water",
    "Museums"
  ],
  "metrics": {
    "overnight_stays": 314193,
    "domestic_share_overnights": 0.7518,
    "summer_temp_avg": 22.32,
    "anchor_stop_name": "Locarno, Piazza Castello",
    "anchor_route_count": 0,
    "hiking_length_15km_km": 1076.68,
    "museum_count_2km": 6,
    "restaurant_count_2km": 63
  },
  "data_status": {
    "bfs": true,
    "climate": true,
    "gtfs": true,
    "hiking": true,
    "water": true,
    "heritage": true,
    "osm": true
  },
  "restaurant_count": 63,
  "isos_name": "",
  "reachable_slugs": [
    "ascona",
    "bellinzona",
    "collina-doro",
    "lugano",
    "mendrisio",
    "monteceneri",
    "muralto",
    "paradiso"
  ]
}