{
  "slug": "locarno",
  "name": "Locarno",
  "canton": "TI",
  "score_total": 64.53,
  "scores": {
    "total": 64.53,
    "base": 63.35,
    "access": 66.31,
    "sub": {
      "anti_overtourism": 92.18,
      "walkability": 14.43,
      "local_hiking": 37.42,
      "water": 95.11,
      "heritage": 50.0,
      "climate": 50.0,
      "scenic_transport": 15.79,
      "destination_pull": 87.75,
      "cultural_access": 100.0,
      "access_hiking": 68.3
    }
  },
  "reachable_tags": [
    "Hiking",
    "Water",
    "Scenic transport",
    "Museums",
    "Historic town"
  ],
  "metrics": {
    "overnight_stays": 314193,
    "domestic_share_overnights": 0.7518,
    "summer_temp_avg": 22.32,
    "local_hiking_m": 64636.5,
    "regional_hiking_m": 1658408.8,
    "walkability_path_m": 12314.6,
    "scenic_transport_count": 15,
    "reachable_named_museums": "20",
    "isos_name": "Locarno",
    "isos_kategorie": "città"
  },
  "data_status": {
    "bfs": true,
    "climate": true,
    "water": true,
    "heritage": true,
    "hiking": true,
    "walkability": true,
    "scenic": true,
    "dest_pull": true,
    "cultural": true
  },
  "rank": 4,
  "seasonality": {
    "volatility_label": "Mildly seasonal",
    "peak_month": "jul",
    "trough_month": "jan",
    "peak_trough_ratio": 4.65,
    "monthly_index": [
      36,
      42,
      70,
      111,
      122,
      130,
      165,
      151,
      140,
      120,
      56,
      59
    ]
  },
  "tourism_intensity": 16.8,
  "restaurant_count": 63,
  "isos_name": "Locarno",
  "reachable_slugs": [
    "ascona",
    "bellinzona",
    "collina-doro",
    "lugano",
    "mendrisio",
    "monteceneri",
    "muralto",
    "paradiso"
  ]
}